[{"storeID":98055,"salesPersonID":14,"cdID":654123,"pricePaid":6,"date":1649569411434},{"storeID":98007,"salesPersonID":6,"cdID":621453,"pricePaid":11,"date":1649569411460},{"storeID":98055,"salesPersonID":14,"cdID":354126,"pricePaid":10,"date":1649569411486},{"storeID":98053,"salesPersonID":4,"cdID":321654,"pricePaid":7,"date":1649569411512},{"storeID":98055,"salesPersonID":16,"cdID":654321,"pricePaid":7,"date":1649569411538},{"storeID":98011,"salesPersonID":17,"cdID":321456,"pricePaid":9,"date":1649569411565},{"storeID":98053,"salesPersonID":1,"cdID":654123,"pricePaid":6,"date":1649569411592},{"storeID":98055,"salesPersonID":14,"cdID":123456,"pricePaid":12,"date":1649569411618},{"storeID":98011,"salesPersonID":17,"cdID":623451,"pricePaid":14,"date":1649569411646},{"storeID":98011,"salesPersonID":18,"cdID":321456,"pricePaid":12,"date":1649569411673},{"storeID":98011,"salesPersonID":18,"cdID":321456,"pricePaid":15,"date":1649569411701},{"storeID":98011,"salesPersonID":20,"cdID":123456,"pricePaid":10,"date":1649569411727},{"storeID":98053,"salesPersonID":4,"cdID":123456,"pricePaid":10,"date":1649569411754},{"storeID":98055,"salesPersonID":14,"cdID":321456,"pricePaid":5,"date":1649569411781},{"storeID":98053,"salesPersonID":1,"cdID":321456,"pricePaid":7,"date":1649569411810},{"storeID":98077,"salesPersonID":9,"cdID":621453,"pricePaid":15,"date":1649569411840},{"storeID":98077,"salesPersonID":12,"cdID":321654,"pricePaid":15,"date":1649569411869},{"storeID":98046,"salesPersonID":23,"cdID":654321,"pricePaid":5,"date":1649569411897},{"storeID":98007,"salesPersonID":5,"cdID":123456,"pricePaid":13,"date":1649569411926},{"storeID":98046,"salesPersonID":22,"cdID":621453,"pricePaid":9,"date":1649569411955},{"storeID":98053,"salesPersonID":4,"cdID":654123,"pricePaid":7,"date":1649569411985},{"storeID":98046,"salesPersonID":23,"cdID":654123,"pricePaid":13,"date":1649569412014},{"storeID":98053,"salesPersonID":3,"cdID":654123,"pricePaid":13,"date":1649569412040},{"storeID":98007,"salesPersonID":5,"cdID":321654,"pricePaid":11,"date":1649569412067},{"storeID":98046,"salesPersonID":21,"cdID":621453,"pricePaid":9,"date":1649569412097},{"storeID":98077,"salesPersonID":9,"cdID":321654,"pricePaid":13,"date":1649569412127},{"storeID":98053,"salesPersonID":4,"cdID":123654,"pricePaid":11,"date":1649569412157},{"storeID":98011,"salesPersonID":19,"cdID":654321,"pricePaid":9,"date":1649569412187},{"storeID":98046,"salesPersonID":23,"cdID":654321,"pricePaid":12,"date":1649569412216},{"storeID":98053,"salesPersonID":1,"cdID":654123,"pricePaid":9,"date":1649569412244},{"storeID":98055,"salesPersonID":15,"cdID":543216,"pricePaid":7,"date":1649569412270},{"storeID":98007,"salesPersonID":5,"cdID":621453,"pricePaid":9,"date":1649569412299},{"storeID":98055,"salesPersonID":16,"cdID":543216,"pricePaid":12,"date":1649569412327},{"storeID":98077,"salesPersonID":10,"cdID":621453,"pricePaid":15,"date":1649569412353},{"storeID":98011,"salesPersonID":20,"cdID":321456,"pricePaid":15,"date":1649569412379},{"storeID":98011,"salesPersonID":20,"cdID":621453,"pricePaid":12,"date":1649569412407},{"storeID":98053,"salesPersonID":2,"cdID":543216,"pricePaid":14,"date":1649569412433},{"storeID":98011,"salesPersonID":19,"cdID":654321,"pricePaid":5,"date":1649569412463},{"storeID":98055,"salesPersonID":15,"cdID":123456,"pricePaid":13,"date":1649569412493},{"storeID":98046,"salesPersonID":21,"cdID":321456,"pricePaid":6,"date":1649569412519},{"storeID":98053,"salesPersonID":3,"cdID":354126,"pricePaid":7,"date":1649569412545},{"storeID":98077,"salesPersonID":11,"cdID":123456,"pricePaid":5,"date":1649569412571},{"storeID":98055,"salesPersonID":15,"cdID":623451,"pricePaid":12,"date":1649569412601},{"storeID":98046,"salesPersonID":21,"cdID":321456,"pricePaid":15,"date":1649569412629},{"storeID":98053,"salesPersonID":3,"cdID":321654,"pricePaid":5,"date":1649569412659},{"storeID":98053,"salesPersonID":4,"cdID":123654,"pricePaid":13,"date":1649569412688},{"storeID":98053,"salesPersonID":3,"cdID":543216,"pricePaid":14,"date":1649569412714},{"storeID":98077,"salesPersonID":9,"cdID":321456,"pricePaid":11,"date":1649569412743},{"storeID":98077,"salesPersonID":12,"cdID":123456,"pricePaid":6,"date":1649569412772},{"storeID":98055,"salesPersonID":15,"cdID":621453,"pricePaid":9,"date":1649569412800},{"storeID":98053,"salesPersonID":3,"cdID":621453,"pricePaid":5,"date":1649569412830},{"storeID":98077,"salesPersonID":11,"cdID":654123,"pricePaid":15,"date":1649569412860},{"storeID":98055,"salesPersonID":16,"cdID":621453,"pricePaid":15,"date":1649569412889},{"storeID":98011,"salesPersonID":19,"cdID":654123,"pricePaid":6,"date":1649569412915},{"storeID":98046,"salesPersonID":22,"cdID":123456,"pricePaid":12,"date":1649569412943},{"storeID":98007,"salesPersonID":5,"cdID":623451,"pricePaid":7,"date":1649569412973},{"storeID":98046,"salesPersonID":21,"cdID":654321,"pricePaid":9,"date":1649569413000},{"storeID":98055,"salesPersonID":15,"cdID":354126,"pricePaid":14,"date":1649569413027},{"storeID":98007,"salesPersonID":8,"cdID":654321,"pricePaid":7,"date":1649569413054},{"storeID":98046,"salesPersonID":24,"cdID":623451,"pricePaid":11,"date":1649569413080},{"storeID":98055,"salesPersonID":16,"cdID":123654,"pricePaid":13,"date":1649569413108},{"storeID":98011,"salesPersonID":19,"cdID":623451,"pricePaid":7,"date":1649569413138},{"storeID":98011,"salesPersonID":17,"cdID":621453,"pricePaid":12,"date":1649569413165},{"storeID":98055,"salesPersonID":14,"cdID":123456,"pricePaid":10,"date":1649569413192},{"storeID":98055,"salesPersonID":13,"cdID":623451,"pricePaid":14,"date":1649569413219},{"storeID":98046,"salesPersonID":22,"cdID":321456,"pricePaid":13,"date":1649569413247},{"storeID":98077,"salesPersonID":12,"cdID":321654,"pricePaid":13,"date":1649569413273},{"storeID":98011,"salesPersonID":19,"cdID":654321,"pricePaid":7,"date":1649569413300},{"storeID":98077,"salesPersonID":9,"cdID":654321,"pricePaid":13,"date":1649569413328},{"storeID":98011,"salesPersonID":20,"cdID":623451,"pricePaid":13,"date":1649569413355},{"storeID":98077,"salesPersonID":9,"cdID":123456,"pricePaid":10,"date":1649569413385},{"storeID":98046,"salesPersonID":21,"cdID":123654,"pricePaid":11,"date":1649569413413},{"storeID":98046,"salesPersonID":24,"cdID":543216,"pricePaid":12,"date":1649569413443},{"storeID":98077,"salesPersonID":9,"cdID":123654,"pricePaid":11,"date":1649569413470},{"storeID":98053,"salesPersonID":4,"cdID":354126,"pricePaid":9,"date":1649569413496},{"storeID":98007,"salesPersonID":5,"cdID":123654,"pricePaid":14,"date":1649569413524},{"storeID":98053,"salesPersonID":2,"cdID":123456,"pricePaid":7,"date":1649569413554},{"storeID":98077,"salesPersonID":9,"cdID":123654,"pricePaid":13,"date":1649569413584},{"storeID":98046,"salesPersonID":24,"cdID":321456,"pricePaid":7,"date":1649569413614},{"storeID":98077,"salesPersonID":11,"cdID":321456,"pricePaid":10,"date":1649569413644},{"storeID":98053,"salesPersonID":3,"cdID":123456,"pricePaid":7,"date":1649569413672},{"storeID":98077,"salesPersonID":12,"cdID":621453,"pricePaid":14,"date":1649569413702},{"storeID":98053,"salesPersonID":3,"cdID":321654,"pricePaid":5,"date":1649569413730},{"storeID":98053,"salesPersonID":2,"cdID":321654,"pricePaid":9,"date":1649569413760},{"storeID":98007,"salesPersonID":8,"cdID":621453,"pricePaid":5,"date":1649569413787},{"storeID":98077,"salesPersonID":11,"cdID":321654,"pricePaid":14,"date":1649569413816},{"storeID":98055,"salesPersonID":16,"cdID":654321,"pricePaid":12,"date":1649569413846},{"storeID":98053,"salesPersonID":4,"cdID":321456,"pricePaid":10,"date":1649569413875},{"storeID":98011,"salesPersonID":20,"cdID":623451,"pricePaid":14,"date":1649569413902},{"storeID":98046,"salesPersonID":24,"cdID":654123,"pricePaid":14,"date":1649569413931},{"storeID":98007,"salesPersonID":8,"cdID":123654,"pricePaid":11,"date":1649569413959},{"storeID":98055,"salesPersonID":15,"cdID":123654,"pricePaid":9,"date":1649569413989},{"storeID":98053,"salesPersonID":2,"cdID":123456,"pricePaid":6,"date":1649569414017},{"storeID":98053,"salesPersonID":3,"cdID":354126,"pricePaid":5,"date":1649569414044},{"storeID":98077,"salesPersonID":11,"cdID":654123,"pricePaid":7,"date":1649569414072},{"storeID":98046,"salesPersonID":23,"cdID":621453,"pricePaid":9,"date":1649569414101},{"storeID":98053,"salesPersonID":3,"cdID":354126,"pricePaid":14,"date":1649569414129},{"storeID":98053,"salesPersonID":3,"cdID":321456,"pricePaid":15,"date":1649569414157},{"storeID":98011,"salesPersonID":18,"cdID":354126,"pricePaid":8,"date":1649569414185},{"storeID":98011,"salesPersonID":18,"cdID":123456,"pricePaid":7,"date":1649569414215},{"storeID":98055,"salesPersonID":14,"cdID":654321,"pricePaid":14,"date":1649569414243},{"storeID":98077,"salesPersonID":12,"cdID":123654,"pricePaid":6,"date":1649569414273},{"storeID":98046,"salesPersonID":21,"cdID":621453,"pricePaid":14,"date":1649569414303},{"storeID":98053,"salesPersonID":2,"cdID":321456,"pricePaid":13,"date":1649569414331},{"storeID":98055,"salesPersonID":15,"cdID":321654,"pricePaid":13,"date":1649569414359},{"storeID":98055,"salesPersonID":13,"cdID":321654,"pricePaid":7,"date":1649569414387},{"storeID":98011,"salesPersonID":17,"cdID":654123,"pricePaid":13,"date":1649569414417},{"storeID":98055,"salesPersonID":13,"cdID":123456,"pricePaid":12,"date":1649569414446},{"storeID":98046,"salesPersonID":21,"cdID":623451,"pricePaid":10,"date":1649569414473},{"storeID":98053,"salesPersonID":4,"cdID":623451,"pricePaid":5,"date":1649569414503},{"storeID":98011,"salesPersonID":19,"cdID":654123,"pricePaid":15,"date":1649569414531},{"storeID":98055,"salesPersonID":14,"cdID":654123,"pricePaid":14,"date":1649569414560},{"storeID":98055,"salesPersonID":15,"cdID":321456,"pricePaid":9,"date":1649569414588},{"storeID":98046,"salesPersonID":21,"cdID":543216,"pricePaid":15,"date":1649569414616},{"storeID":98077,"salesPersonID":12,"cdID":621453,"pricePaid":11,"date":1649569414642},{"storeID":98055,"salesPersonID":13,"cdID":543216,"pricePaid":6,"date":1649569414669},{"storeID":98011,"salesPersonID":18,"cdID":321456,"pricePaid":11,"date":1649569414699},{"storeID":98011,"salesPersonID":17,"cdID":623451,"pricePaid":7,"date":1649569414727},{"storeID":98053,"salesPersonID":1,"cdID":621453,"pricePaid":7,"date":1649569414753},{"storeID":98077,"salesPersonID":12,"cdID":654321,"pricePaid":7,"date":1649569414783},{"storeID":98007,"salesPersonID":7,"cdID":543216,"pricePaid":14,"date":1649569414811},{"storeID":98077,"salesPersonID":12,"cdID":543216,"pricePaid":9,"date":1649569414839},{"storeID":98055,"salesPersonID":13,"cdID":123654,"pricePaid":10,"date":1649569414867},{"storeID":98046,"salesPersonID":22,"cdID":623451,"pricePaid":15,"date":1649569414895},{"storeID":98007,"salesPersonID":8,"cdID":654123,"pricePaid":15,"date":1649569414922},{"storeID":98077,"salesPersonID":11,"cdID":654123,"pricePaid":5,"date":1649569414948},{"storeID":98053,"salesPersonID":4,"cdID":623451,"pricePaid":13,"date":1649569414977},{"storeID":98011,"salesPersonID":18,"cdID":654123,"pricePaid":10,"date":1649569415003},{"storeID":98046,"salesPersonID":22,"cdID":123456,"pricePaid":7,"date":1649569415033},{"storeID":98053,"salesPersonID":1,"cdID":354126,"pricePaid":12,"date":1649569415061},{"storeID":98053,"salesPersonID":4,"cdID":123654,"pricePaid":12,"date":1649569415088},{"storeID":98007,"salesPersonID":6,"cdID":621453,"pricePaid":7,"date":1649569415114},{"storeID":98055,"salesPersonID":13,"cdID":123456,"pricePaid":13,"date":1649569415144},{"storeID":98077,"salesPersonID":12,"cdID":354126,"pricePaid":5,"date":1649569415171},{"storeID":98055,"salesPersonID":13,"cdID":623451,"pricePaid":11,"date":1649569415197},{"storeID":98055,"salesPersonID":14,"cdID":621453,"pricePaid":9,"date":1649569415225},{"storeID":98053,"salesPersonID":4,"cdID":354126,"pricePaid":6,"date":1649569415255},{"storeID":98046,"salesPersonID":22,"cdID":623451,"pricePaid":6,"date":1649569415284},{"storeID":98011,"salesPersonID":17,"cdID":654123,"pricePaid":7,"date":1649569415311},{"storeID":98077,"salesPersonID":9,"cdID":654123,"pricePaid":13,"date":1649569415339},{"storeID":98055,"salesPersonID":14,"cdID":354126,"pricePaid":7,"date":1649569415369},{"storeID":98046,"salesPersonID":21,"cdID":123456,"pricePaid":14,"date":1649569415398},{"storeID":98077,"salesPersonID":12,"cdID":123654,"pricePaid":9,"date":1649569415427},{"storeID":98055,"salesPersonID":14,"cdID":321654,"pricePaid":11,"date":1649569415457},{"storeID":98077,"salesPersonID":11,"cdID":621453,"pricePaid":8,"date":1649569415483},{"storeID":98053,"salesPersonID":3,"cdID":123456,"pricePaid":7,"date":1649569415509},{"storeID":98077,"salesPersonID":11,"cdID":321456,"pricePaid":11,"date":1649569415538},{"storeID":98011,"salesPersonID":17,"cdID":123654,"pricePaid":5,"date":1649569415567},{"storeID":98046,"salesPersonID":24,"cdID":654321,"pricePaid":7,"date":1649569415593},{"storeID":98077,"salesPersonID":9,"cdID":621453,"pricePaid":5,"date":1649569415622},{"storeID":98046,"salesPersonID":23,"cdID":321456,"pricePaid":9,"date":1649569415650},{"storeID":98055,"salesPersonID":15,"cdID":654321,"pricePaid":7,"date":1649569415677},{"storeID":98007,"salesPersonID":7,"cdID":123456,"pricePaid":8,"date":1649569415704},{"storeID":98055,"salesPersonID":13,"cdID":123654,"pricePaid":6,"date":1649569415730},{"storeID":98011,"salesPersonID":17,"cdID":123456,"pricePaid":8,"date":1649569415758},{"storeID":98007,"salesPersonID":6,"cdID":354126,"pricePaid":11,"date":1649569415786},{"storeID":98077,"salesPersonID":9,"cdID":321654,"pricePaid":13,"date":1649569415813},{"storeID":98007,"salesPersonID":6,"cdID":623451,"pricePaid":5,"date":1649569415842},{"storeID":98077,"salesPersonID":12,"cdID":654123,"pricePaid":13,"date":1649569415871},{"storeID":98053,"salesPersonID":1,"cdID":354126,"pricePaid":12,"date":1649569415897},{"storeID":98053,"salesPersonID":3,"cdID":654123,"pricePaid":10,"date":1649569415923},{"storeID":98077,"salesPersonID":10,"cdID":354126,"pricePaid":6,"date":1649569415949},{"storeID":98007,"salesPersonID":8,"cdID":321456,"pricePaid":13,"date":1649569415979},{"storeID":98007,"salesPersonID":7,"cdID":123456,"pricePaid":13,"date":1649569416005},{"storeID":98077,"salesPersonID":9,"cdID":543216,"pricePaid":12,"date":1649569416031},{"storeID":98077,"salesPersonID":9,"cdID":654123,"pricePaid":15,"date":1649569416059},{"storeID":98053,"salesPersonID":4,"cdID":654321,"pricePaid":8,"date":1649569416086},{"storeID":98077,"salesPersonID":9,"cdID":654123,"pricePaid":15,"date":1649569416115},{"storeID":98055,"salesPersonID":15,"cdID":621453,"pricePaid":5,"date":1649569416144},{"storeID":98046,"salesPersonID":23,"cdID":354126,"pricePaid":8,"date":1649569416172},{"storeID":98046,"salesPersonID":24,"cdID":621453,"pricePaid":6,"date":1649569416201},{"storeID":98046,"salesPersonID":22,"cdID":123456,"pricePaid":10,"date":1649569416231},{"storeID":98053,"salesPersonID":4,"cdID":123654,"pricePaid":12,"date":1649569416260},{"storeID":98077,"salesPersonID":9,"cdID":621453,"pricePaid":10,"date":1649569416286},{"storeID":98046,"salesPersonID":23,"cdID":123654,"pricePaid":7,"date":1649569416314},{"storeID":98053,"salesPersonID":2,"cdID":354126,"pricePaid":9,"date":1649569416344},{"storeID":98046,"salesPersonID":24,"cdID":123456,"pricePaid":8,"date":1649569416371},{"storeID":98053,"salesPersonID":1,"cdID":623451,"pricePaid":6,"date":1649569416401},{"storeID":98011,"salesPersonID":19,"cdID":654321,"pricePaid":5,"date":1649569416429},{"storeID":98046,"salesPersonID":22,"cdID":654123,"pricePaid":8,"date":1649569416458},{"storeID":98055,"salesPersonID":15,"cdID":654123,"pricePaid":15,"date":1649569416486},{"storeID":98011,"salesPersonID":20,"cdID":623451,"pricePaid":14,"date":1649569416514},{"storeID":98077,"salesPersonID":12,"cdID":354126,"pricePaid":6,"date":1649569416541},{"storeID":98007,"salesPersonID":7,"cdID":321654,"pricePaid":9,"date":1649569416569},{"storeID":98053,"salesPersonID":3,"cdID":621453,"pricePaid":8,"date":1649569416595},{"storeID":98007,"salesPersonID":8,"cdID":543216,"pricePaid":11,"date":1649569416625},{"storeID":98046,"salesPersonID":22,"cdID":321456,"pricePaid":11,"date":1649569416652},{"storeID":98011,"salesPersonID":17,"cdID":621453,"pricePaid":8,"date":1649569416682},{"storeID":98046,"salesPersonID":24,"cdID":654321,"pricePaid":9,"date":1649569416710},{"storeID":98053,"salesPersonID":1,"cdID":654123,"pricePaid":5,"date":1649569416738},{"storeID":98077,"salesPersonID":11,"cdID":321654,"pricePaid":13,"date":1649569416765},{"storeID":98077,"salesPersonID":10,"cdID":321456,"pricePaid":10,"date":1649569416792},{"storeID":98077,"salesPersonID":9,"cdID":123456,"pricePaid":6,"date":1649569416819},{"storeID":98007,"salesPersonID":6,"cdID":123456,"pricePaid":13,"date":1649569416845},{"storeID":98055,"salesPersonID":14,"cdID":543216,"pricePaid":10,"date":1649569416874},{"storeID":98046,"salesPersonID":21,"cdID":543216,"pricePaid":7,"date":1649569416902},{"storeID":98011,"salesPersonID":19,"cdID":654123,"pricePaid":7,"date":1649569416928},{"storeID":98055,"salesPersonID":13,"cdID":321654,"pricePaid":15,"date":1649569416956},{"storeID":98055,"salesPersonID":15,"cdID":123456,"pricePaid":14,"date":1649569416982},{"storeID":98055,"salesPersonID":16,"cdID":621453,"pricePaid":10,"date":1649569417009},{"storeID":98011,"salesPersonID":18,"cdID":543216,"pricePaid":11,"date":1649569417036},{"storeID":98046,"salesPersonID":24,"cdID":321654,"pricePaid":12,"date":1649569417065},{"storeID":98053,"salesPersonID":1,"cdID":654123,"pricePaid":12,"date":1649569417093},{"storeID":98053,"salesPersonID":4,"cdID":621453,"pricePaid":8,"date":1649569417122},{"storeID":98011,"salesPersonID":20,"cdID":123654,"pricePaid":8,"date":1649569417152},{"storeID":98077,"salesPersonID":11,"cdID":621453,"pricePaid":10,"date":1649569417182},{"storeID":98077,"salesPersonID":10,"cdID":623451,"pricePaid":13,"date":1649569417212},{"storeID":98046,"salesPersonID":21,"cdID":654321,"pricePaid":12,"date":1649569417240},{"storeID":98011,"salesPersonID":19,"cdID":354126,"pricePaid":15,"date":1649569417270},{"storeID":98011,"salesPersonID":19,"cdID":321654,"pricePaid":5,"date":1649569417300},{"storeID":98046,"salesPersonID":21,"cdID":123456,"pricePaid":9,"date":1649569417326},{"storeID":98007,"salesPersonID":6,"cdID":654123,"pricePaid":13,"date":1649569417353},{"storeID":98007,"salesPersonID":7,"cdID":123654,"pricePaid":10,"date":1649569417383},{"storeID":98011,"salesPersonID":17,"cdID":654321,"pricePaid":7,"date":1649569417409},{"storeID":98007,"salesPersonID":8,"cdID":654123,"pricePaid":13,"date":1649569417435},{"storeID":98046,"salesPersonID":24,"cdID":654123,"pricePaid":9,"date":1649569417461},{"storeID":98077,"salesPersonID":10,"cdID":623451,"pricePaid":15,"date":1649569417491},{"storeID":98011,"salesPersonID":19,"cdID":621453,"pricePaid":15,"date":1649569417521},{"storeID":98011,"salesPersonID":18,"cdID":354126,"pricePaid":14,"date":1649569417550},{"storeID":98011,"salesPersonID":18,"cdID":123654,"pricePaid":11,"date":1649569417580},{"storeID":98077,"salesPersonID":11,"cdID":123456,"pricePaid":5,"date":1649569417607},{"storeID":98053,"salesPersonID":1,"cdID":654321,"pricePaid":11,"date":1649569417636},{"storeID":98011,"salesPersonID":19,"cdID":654123,"pricePaid":12,"date":1649569417666},{"storeID":98007,"salesPersonID":7,"cdID":123654,"pricePaid":11,"date":1649569417693},{"storeID":98053,"salesPersonID":1,"cdID":621453,"pricePaid":7,"date":1649569417720},{"storeID":98007,"salesPersonID":6,"cdID":654321,"pricePaid":11,"date":1649569417748},{"storeID":98011,"salesPersonID":18,"cdID":654321,"pricePaid":12,"date":1649569417778},{"storeID":98055,"salesPersonID":16,"cdID":543216,"pricePaid":10,"date":1649569417805},{"storeID":98053,"salesPersonID":2,"cdID":123456,"pricePaid":14,"date":1649569417834},{"storeID":98053,"salesPersonID":2,"cdID":543216,"pricePaid":11,"date":1649569417862},{"storeID":98046,"salesPersonID":23,"cdID":321654,"pricePaid":10,"date":1649569417888},{"storeID":98011,"salesPersonID":20,"cdID":321654,"pricePaid":15,"date":1649569417916},{"storeID":98011,"salesPersonID":17,"cdID":354126,"pricePaid":14,"date":1649569417946},{"storeID":98007,"salesPersonID":6,"cdID":123654,"pricePaid":14,"date":1649569417973},{"storeID":98011,"salesPersonID":17,"cdID":123456,"pricePaid":6,"date":1649569418002},{"storeID":98053,"salesPersonID":4,"cdID":543216,"pricePaid":13,"date":1649569418031},{"storeID":98007,"salesPersonID":6,"cdID":621453,"pricePaid":13,"date":1649569418058},{"storeID":98055,"salesPersonID":14,"cdID":321456,"pricePaid":12,"date":1649569418086},{"storeID":98053,"salesPersonID":1,"cdID":123654,"pricePaid":10,"date":1649569418115},{"storeID":98046,"salesPersonID":23,"cdID":321654,"pricePaid":13,"date":1649569418141},{"storeID":98007,"salesPersonID":8,"cdID":654123,"pricePaid":6,"date":1649569418167},{"storeID":98007,"salesPersonID":6,"cdID":654123,"pricePaid":12,"date":1649569418193},{"storeID":98077,"salesPersonID":12,"cdID":123654,"pricePaid":5,"date":1649569418220},{"storeID":98055,"salesPersonID":13,"cdID":123456,"pricePaid":12,"date":1649569418246},{"storeID":98046,"salesPersonID":22,"cdID":654123,"pricePaid":5,"date":1649569418275},{"storeID":98007,"salesPersonID":7,"cdID":123654,"pricePaid":11,"date":1649569418305},{"storeID":98007,"salesPersonID":6,"cdID":654123,"pricePaid":14,"date":1649569418332},{"storeID":98055,"salesPersonID":16,"cdID":621453,"pricePaid":8,"date":1649569418359},{"storeID":98011,"salesPersonID":20,"cdID":354126,"pricePaid":15,"date":1649569418389},{"storeID":98077,"salesPersonID":11,"cdID":543216,"pricePaid":9,"date":1649569418415},{"storeID":98007,"salesPersonID":5,"cdID":543216,"pricePaid":12,"date":1649569418441},{"storeID":98055,"salesPersonID":14,"cdID":123456,"pricePaid":8,"date":1649569418471},{"storeID":98055,"salesPersonID":15,"cdID":123456,"pricePaid":8,"date":1649569418498},{"storeID":98077,"salesPersonID":12,"cdID":123654,"pricePaid":8,"date":1649569418528},{"storeID":98055,"salesPersonID":16,"cdID":623451,"pricePaid":10,"date":1649569418558},{"storeID":98077,"salesPersonID":9,"cdID":623451,"pricePaid":6,"date":1649569418586},{"storeID":98053,"salesPersonID":2,"cdID":543216,"pricePaid":9,"date":1649569418616},{"storeID":98055,"salesPersonID":14,"cdID":123654,"pricePaid":9,"date":1649569418642},{"storeID":98046,"salesPersonID":23,"cdID":123456,"pricePaid":12,"date":1649569418669},{"storeID":98053,"salesPersonID":1,"cdID":623451,"pricePaid":14,"date":1649569418699},{"storeID":98046,"salesPersonID":22,"cdID":621453,"pricePaid":10,"date":1649569418726},{"storeID":98011,"salesPersonID":17,"cdID":543216,"pricePaid":14,"date":1649569418754},{"storeID":98011,"salesPersonID":18,"cdID":321654,"pricePaid":5,"date":1649569418780},{"storeID":98055,"salesPersonID":14,"cdID":321456,"pricePaid":15,"date":1649569418808},{"storeID":98011,"salesPersonID":19,"cdID":123654,"pricePaid":7,"date":1649569418836},{"storeID":98053,"salesPersonID":3,"cdID":123456,"pricePaid":15,"date":1649569418866},{"storeID":98053,"salesPersonID":3,"cdID":321456,"pricePaid":11,"date":1649569418895},{"storeID":98055,"salesPersonID":14,"cdID":123654,"pricePaid":15,"date":1649569418924},{"storeID":98046,"salesPersonID":23,"cdID":354126,"pricePaid":5,"date":1649569418954},{"storeID":98055,"salesPersonID":15,"cdID":354126,"pricePaid":6,"date":1649569418981},{"storeID":98055,"salesPersonID":13,"cdID":354126,"pricePaid":11,"date":1649569419009},{"storeID":98011,"salesPersonID":17,"cdID":623451,"pricePaid":13,"date":1649569419035},{"storeID":98007,"salesPersonID":8,"cdID":654123,"pricePaid":15,"date":1649569419065},{"storeID":98053,"salesPersonID":2,"cdID":321456,"pricePaid":14,"date":1649569419095},{"storeID":98055,"salesPersonID":16,"cdID":321456,"pricePaid":13,"date":1649569419122},{"storeID":98046,"salesPersonID":23,"cdID":543216,"pricePaid":12,"date":1649569419151},{"storeID":98077,"salesPersonID":9,"cdID":123456,"pricePaid":7,"date":1649569419178},{"storeID":98007,"salesPersonID":8,"cdID":123456,"pricePaid":6,"date":1649569419205},{"storeID":98053,"salesPersonID":3,"cdID":321654,"pricePaid":7,"date":1649569419232},{"storeID":98011,"salesPersonID":18,"cdID":123456,"pricePaid":6,"date":1649569419260},{"storeID":98053,"salesPersonID":1,"cdID":621453,"pricePaid":8,"date":1649569419289},{"storeID":98011,"salesPersonID":17,"cdID":654321,"pricePaid":11,"date":1649569419318},{"storeID":98055,"salesPersonID":16,"cdID":321456,"pricePaid":7,"date":1649569419345},{"storeID":98007,"salesPersonID":5,"cdID":543216,"pricePaid":10,"date":1649569419371},{"storeID":98011,"salesPersonID":19,"cdID":654321,"pricePaid":14,"date":1649569419399},{"storeID":98007,"salesPersonID":6,"cdID":123456,"pricePaid":7,"date":1649569419425},{"storeID":98007,"salesPersonID":5,"cdID":543216,"pricePaid":13,"date":1649569419453},{"storeID":98077,"salesPersonID":11,"cdID":623451,"pricePaid":13,"date":1649569419481},{"storeID":98011,"salesPersonID":20,"cdID":654321,"pricePaid":8,"date":1649569419509},{"storeID":98011,"salesPersonID":20,"cdID":621453,"pricePaid":5,"date":1649569419535},{"storeID":98055,"salesPersonID":13,"cdID":354126,"pricePaid":9,"date":1649569419563},{"storeID":98007,"salesPersonID":5,"cdID":621453,"pricePaid":15,"date":1649569419589},{"storeID":98077,"salesPersonID":12,"cdID":123456,"pricePaid":8,"date":1649569419615},{"storeID":98053,"salesPersonID":3,"cdID":321654,"pricePaid":13,"date":1649569419645},{"storeID":98007,"salesPersonID":7,"cdID":654321,"pricePaid":14,"date":1649569419671},{"storeID":98007,"salesPersonID":6,"cdID":123654,"pricePaid":5,"date":1649569419700},{"storeID":98077,"salesPersonID":9,"cdID":123654,"pricePaid":7,"date":1649569419726},{"storeID":98055,"salesPersonID":15,"cdID":543216,"pricePaid":8,"date":1649569419752},{"storeID":98077,"salesPersonID":10,"cdID":621453,"pricePaid":6,"date":1649569419781},{"storeID":98007,"salesPersonID":5,"cdID":354126,"pricePaid":11,"date":1649569419809},{"storeID":98046,"salesPersonID":22,"cdID":123654,"pricePaid":14,"date":1649569419839},{"storeID":98011,"salesPersonID":19,"cdID":123456,"pricePaid":6,"date":1649569419867},{"storeID":98055,"salesPersonID":13,"cdID":654123,"pricePaid":10,"date":1649569419896},{"storeID":98007,"salesPersonID":8,"cdID":654321,"pricePaid":9,"date":1649569419924},{"storeID":98053,"salesPersonID":4,"cdID":654123,"pricePaid":15,"date":1649569419951},{"storeID":98046,"salesPersonID":22,"cdID":654123,"pricePaid":11,"date":1649569419981},{"storeID":98011,"salesPersonID":17,"cdID":123654,"pricePaid":7,"date":1649569420007},{"storeID":98055,"salesPersonID":14,"cdID":623451,"pricePaid":15,"date":1649569420036},{"storeID":98011,"salesPersonID":18,"cdID":654321,"pricePaid":6,"date":1649569420065},{"storeID":98077,"salesPersonID":11,"cdID":654321,"pricePaid":7,"date":1649569420093},{"storeID":98007,"salesPersonID":6,"cdID":654123,"pricePaid":11,"date":1649569420120},{"storeID":98053,"salesPersonID":1,"cdID":543216,"pricePaid":10,"date":1649569420148},{"storeID":98055,"salesPersonID":15,"cdID":543216,"pricePaid":5,"date":1649569420176},{"storeID":98055,"salesPersonID":13,"cdID":621453,"pricePaid":8,"date":1649569420206},{"storeID":98007,"salesPersonID":6,"cdID":623451,"pricePaid":10,"date":1649569420233},{"storeID":98053,"salesPersonID":4,"cdID":621453,"pricePaid":5,"date":1649569420263},{"storeID":98046,"salesPersonID":24,"cdID":623451,"pricePaid":7,"date":1649569420290},{"storeID":98055,"salesPersonID":16,"cdID":123654,"pricePaid":13,"date":1649569420320},{"storeID":98011,"salesPersonID":20,"cdID":321654,"pricePaid":7,"date":1649569420349},{"storeID":98077,"salesPersonID":10,"cdID":123456,"pricePaid":14,"date":1649569420377},{"storeID":98053,"salesPersonID":4,"cdID":654321,"pricePaid":13,"date":1649569420404},{"storeID":98046,"salesPersonID":23,"cdID":623451,"pricePaid":7,"date":1649569420432},{"storeID":98053,"salesPersonID":3,"cdID":654321,"pricePaid":11,"date":1649569420460},{"storeID":98053,"salesPersonID":1,"cdID":123456,"pricePaid":14,"date":1649569420488},{"storeID":98007,"salesPersonID":8,"cdID":321654,"pricePaid":12,"date":1649569420516},{"storeID":98011,"salesPersonID":19,"cdID":123456,"pricePaid":13,"date":1649569420543},{"storeID":98053,"salesPersonID":4,"cdID":321654,"pricePaid":5,"date":1649569420570},{"storeID":98011,"salesPersonID":17,"cdID":123456,"pricePaid":6,"date":1649569420600},{"storeID":98007,"salesPersonID":8,"cdID":623451,"pricePaid":10,"date":1649569420628},{"storeID":98011,"salesPersonID":20,"cdID":654321,"pricePaid":7,"date":1649569420656},{"storeID":98055,"salesPersonID":13,"cdID":321456,"pricePaid":10,"date":1649569420683},{"storeID":98053,"salesPersonID":2,"cdID":354126,"pricePaid":10,"date":1649569420713},{"storeID":98011,"salesPersonID":20,"cdID":123456,"pricePaid":6,"date":1649569420740},{"storeID":98011,"salesPersonID":17,"cdID":543216,"pricePaid":9,"date":1649569420766},{"storeID":98046,"salesPersonID":23,"cdID":623451,"pricePaid":8,"date":1649569420796},{"storeID":98046,"salesPersonID":23,"cdID":543216,"pricePaid":10,"date":1649569420824},{"storeID":98055,"salesPersonID":15,"cdID":321456,"pricePaid":5,"date":1649569420852},{"storeID":98053,"salesPersonID":4,"cdID":623451,"pricePaid":5,"date":1649569420878},{"storeID":98077,"salesPersonID":9,"cdID":123654,"pricePaid":14,"date":1649569420907},{"storeID":98053,"salesPersonID":3,"cdID":123456,"pricePaid":15,"date":1649569420937},{"storeID":98077,"salesPersonID":9,"cdID":321654,"pricePaid":7,"date":1649569420967},{"storeID":98046,"salesPersonID":23,"cdID":321456,"pricePaid":15,"date":1649569420997},{"storeID":98046,"salesPersonID":22,"cdID":543216,"pricePaid":15,"date":1649569421027},{"storeID":98011,"salesPersonID":19,"cdID":321456,"pricePaid":7,"date":1649569421056},{"storeID":98007,"salesPersonID":8,"cdID":123456,"pricePaid":15,"date":1649569421083},{"storeID":98007,"salesPersonID":5,"cdID":623451,"pricePaid":8,"date":1649569421110},{"storeID":98011,"salesPersonID":20,"cdID":321456,"pricePaid":9,"date":1649569421136},{"storeID":98046,"salesPersonID":24,"cdID":354126,"pricePaid":10,"date":1649569421165},{"storeID":98055,"salesPersonID":15,"cdID":123456,"pricePaid":7,"date":1649569421192},{"storeID":98007,"salesPersonID":5,"cdID":543216,"pricePaid":15,"date":1649569421219},{"storeID":98046,"salesPersonID":24,"cdID":321654,"pricePaid":13,"date":1649569421247},{"storeID":98053,"salesPersonID":2,"cdID":123456,"pricePaid":8,"date":1649569421275},{"storeID":98007,"salesPersonID":6,"cdID":621453,"pricePaid":12,"date":1649569421305},{"storeID":98046,"salesPersonID":23,"cdID":321654,"pricePaid":6,"date":1649569421333},{"storeID":98011,"salesPersonID":19,"cdID":654123,"pricePaid":13,"date":1649569421362},{"storeID":98053,"salesPersonID":2,"cdID":623451,"pricePaid":12,"date":1649569421391},{"storeID":98053,"salesPersonID":4,"cdID":621453,"pricePaid":11,"date":1649569421420},{"storeID":98055,"salesPersonID":14,"cdID":621453,"pricePaid":7,"date":1649569421446},{"storeID":98077,"salesPersonID":10,"cdID":354126,"pricePaid":12,"date":1649569421476},{"storeID":98007,"salesPersonID":8,"cdID":654321,"pricePaid":15,"date":1649569421503},{"storeID":98077,"salesPersonID":12,"cdID":621453,"pricePaid":15,"date":1649569421532},{"storeID":98046,"salesPersonID":23,"cdID":321654,"pricePaid":14,"date":1649569421560},{"storeID":98046,"salesPersonID":21,"cdID":543216,"pricePaid":10,"date":1649569421589},{"storeID":98053,"salesPersonID":1,"cdID":621453,"pricePaid":11,"date":1649569421617},{"storeID":98077,"salesPersonID":10,"cdID":321456,"pricePaid":6,"date":1649569421646},{"storeID":98053,"salesPersonID":4,"cdID":654321,"pricePaid":12,"date":1649569421672},{"storeID":98055,"salesPersonID":13,"cdID":123654,"pricePaid":6,"date":1649569421701},{"storeID":98077,"salesPersonID":12,"cdID":321654,"pricePaid":15,"date":1649569421727},{"storeID":98007,"salesPersonID":7,"cdID":654321,"pricePaid":6,"date":1649569421757},{"storeID":98046,"salesPersonID":21,"cdID":621453,"pricePaid":15,"date":1649569421783},{"storeID":98007,"salesPersonID":7,"cdID":621453,"pricePaid":8,"date":1649569421812},{"storeID":98011,"salesPersonID":17,"cdID":543216,"pricePaid":13,"date":1649569421841},{"storeID":98011,"salesPersonID":18,"cdID":354126,"pricePaid":8,"date":1649569421869},{"storeID":98053,"salesPersonID":3,"cdID":123654,"pricePaid":14,"date":1649569421898},{"storeID":98055,"salesPersonID":13,"cdID":654123,"pricePaid":13,"date":1649569421927},{"storeID":98055,"salesPersonID":15,"cdID":621453,"pricePaid":5,"date":1649569421954},{"storeID":98046,"salesPersonID":21,"cdID":654123,"pricePaid":10,"date":1649569421983},{"storeID":98053,"salesPersonID":1,"cdID":123456,"pricePaid":13,"date":1649569422013},{"storeID":98053,"salesPersonID":2,"cdID":123456,"pricePaid":9,"date":1649569422043},{"storeID":98007,"salesPersonID":7,"cdID":123456,"pricePaid":12,"date":1649569422070},{"storeID":98055,"salesPersonID":16,"cdID":354126,"pricePaid":5,"date":1649569422097},{"storeID":98053,"salesPersonID":4,"cdID":354126,"pricePaid":14,"date":1649569422126},{"storeID":98077,"salesPersonID":10,"cdID":623451,"pricePaid":14,"date":1649569422156},{"storeID":98077,"salesPersonID":10,"cdID":654123,"pricePaid":14,"date":1649569422186},{"storeID":98007,"salesPersonID":5,"cdID":321456,"pricePaid":11,"date":1649569422212},{"storeID":98077,"salesPersonID":10,"cdID":321654,"pricePaid":5,"date":1649569422242},{"storeID":98077,"salesPersonID":9,"cdID":654123,"pricePaid":13,"date":1649569422268},{"storeID":98053,"salesPersonID":1,"cdID":321456,"pricePaid":12,"date":1649569422294},{"storeID":98046,"salesPersonID":22,"cdID":123456,"pricePaid":13,"date":1649569422320},{"storeID":98055,"salesPersonID":16,"cdID":123456,"pricePaid":11,"date":1649569422350},{"storeID":98007,"salesPersonID":6,"cdID":543216,"pricePaid":5,"date":1649569422377},{"storeID":98053,"salesPersonID":2,"cdID":321654,"pricePaid":6,"date":1649569422405},{"storeID":98011,"salesPersonID":20,"cdID":543216,"pricePaid":12,"date":1649569422433},{"storeID":98055,"salesPersonID":15,"cdID":543216,"pricePaid":12,"date":1649569422460},{"storeID":98077,"salesPersonID":12,"cdID":623451,"pricePaid":15,"date":1649569422486},{"storeID":98007,"salesPersonID":5,"cdID":123456,"pricePaid":12,"date":1649569422516},{"storeID":98077,"salesPersonID":11,"cdID":321456,"pricePaid":14,"date":1649569422544},{"storeID":98007,"salesPersonID":8,"cdID":123456,"pricePaid":7,"date":1649569422571},{"storeID":98011,"salesPersonID":18,"cdID":654123,"pricePaid":12,"date":1649569422597},{"storeID":98053,"salesPersonID":1,"cdID":654321,"pricePaid":5,"date":1649569422624},{"storeID":98053,"salesPersonID":4,"cdID":123654,"pricePaid":12,"date":1649569422654},{"storeID":98007,"salesPersonID":5,"cdID":621453,"pricePaid":5,"date":1649569422680},{"storeID":98011,"salesPersonID":17,"cdID":321654,"pricePaid":12,"date":1649569422706},{"storeID":98053,"salesPersonID":3,"cdID":543216,"pricePaid":5,"date":1649569422733},{"storeID":98011,"salesPersonID":17,"cdID":123456,"pricePaid":8,"date":1649569422762},{"storeID":98011,"salesPersonID":18,"cdID":654321,"pricePaid":14,"date":1649569422791},{"storeID":98007,"salesPersonID":5,"cdID":354126,"pricePaid":6,"date":1649569422819},{"storeID":98011,"salesPersonID":17,"cdID":123654,"pricePaid":13,"date":1649569422845},{"storeID":98011,"salesPersonID":19,"cdID":321654,"pricePaid":12,"date":1649569422875},{"storeID":98046,"salesPersonID":24,"cdID":123654,"pricePaid":11,"date":1649569422903},{"storeID":98077,"salesPersonID":10,"cdID":623451,"pricePaid":8,"date":1649569422932},{"storeID":98011,"salesPersonID":19,"cdID":321456,"pricePaid":13,"date":1649569422961},{"storeID":98011,"salesPersonID":20,"cdID":321654,"pricePaid":7,"date":1649569422987},{"storeID":98053,"salesPersonID":3,"cdID":654123,"pricePaid":5,"date":1649569423016},{"storeID":98011,"salesPersonID":20,"cdID":321654,"pricePaid":13,"date":1649569423045},{"storeID":98077,"salesPersonID":11,"cdID":321456,"pricePaid":8,"date":1649569423074},{"storeID":98053,"salesPersonID":4,"cdID":123456,"pricePaid":7,"date":1649569423103},{"storeID":98011,"salesPersonID":18,"cdID":123456,"pricePaid":8,"date":1649569423130},{"storeID":98046,"salesPersonID":22,"cdID":654123,"pricePaid":15,"date":1649569423157},{"storeID":98055,"salesPersonID":14,"cdID":321456,"pricePaid":15,"date":1649569423187},{"storeID":98007,"salesPersonID":5,"cdID":321456,"pricePaid":6,"date":1649569423215},{"storeID":98077,"salesPersonID":11,"cdID":543216,"pricePaid":13,"date":1649569423244},{"storeID":98053,"salesPersonID":4,"cdID":621453,"pricePaid":8,"date":1649569423272},{"storeID":98053,"salesPersonID":4,"cdID":621453,"pricePaid":5,"date":1649569423300},{"storeID":98077,"salesPersonID":12,"cdID":123456,"pricePaid":8,"date":1649569423330},{"storeID":98055,"salesPersonID":15,"cdID":654123,"pricePaid":11,"date":1649569423356},{"storeID":98077,"salesPersonID":11,"cdID":321456,"pricePaid":5,"date":1649569423385},{"storeID":98046,"salesPersonID":24,"cdID":123654,"pricePaid":15,"date":1649569423412},{"storeID":98011,"salesPersonID":17,"cdID":321456,"pricePaid":11,"date":1649569423440},{"storeID":98053,"salesPersonID":2,"cdID":123654,"pricePaid":7,"date":1649569423469},{"storeID":98053,"salesPersonID":1,"cdID":123456,"pricePaid":7,"date":1649569423498},{"storeID":98055,"salesPersonID":13,"cdID":543216,"pricePaid":15,"date":1649569423527},{"storeID":98011,"salesPersonID":19,"cdID":123654,"pricePaid":10,"date":1649569423556},{"storeID":98046,"salesPersonID":22,"cdID":321654,"pricePaid":14,"date":1649569423583},{"storeID":98055,"salesPersonID":13,"cdID":354126,"pricePaid":14,"date":1649569423609},{"storeID":98046,"salesPersonID":23,"cdID":123654,"pricePaid":9,"date":1649569423638},{"storeID":98046,"salesPersonID":21,"cdID":543216,"pricePaid":8,"date":1649569423665},{"storeID":98053,"salesPersonID":1,"cdID":621453,"pricePaid":14,"date":1649569423692},{"storeID":98053,"salesPersonID":2,"cdID":623451,"pricePaid":13,"date":1649569423718},{"storeID":98077,"salesPersonID":10,"cdID":654321,"pricePaid":8,"date":1649569423748},{"storeID":98046,"salesPersonID":24,"cdID":321456,"pricePaid":11,"date":1649569423775},{"storeID":98053,"salesPersonID":3,"cdID":321456,"pricePaid":7,"date":1649569423804},{"storeID":98011,"salesPersonID":17,"cdID":654321,"pricePaid":15,"date":1649569423834},{"storeID":98007,"salesPersonID":8,"cdID":543216,"pricePaid":11,"date":1649569423861},{"storeID":98077,"salesPersonID":9,"cdID":543216,"pricePaid":11,"date":1649569423890},{"storeID":98077,"salesPersonID":12,"cdID":321654,"pricePaid":6,"date":1649569423920},{"storeID":98046,"salesPersonID":23,"cdID":543216,"pricePaid":13,"date":1649569423950},{"storeID":98046,"salesPersonID":22,"cdID":654123,"pricePaid":9,"date":1649569423977},{"storeID":98055,"salesPersonID":14,"cdID":321456,"pricePaid":9,"date":1649569424003},{"storeID":98077,"salesPersonID":9,"cdID":543216,"pricePaid":14,"date":1649569424033},{"storeID":98077,"salesPersonID":12,"cdID":123654,"pricePaid":9,"date":1649569424062},{"storeID":98055,"salesPersonID":13,"cdID":321654,"pricePaid":11,"date":1649569424091},{"storeID":98077,"salesPersonID":11,"cdID":123456,"pricePaid":7,"date":1649569424119},{"storeID":98077,"salesPersonID":10,"cdID":543216,"pricePaid":11,"date":1649569424145},{"storeID":98053,"salesPersonID":3,"cdID":654123,"pricePaid":7,"date":1649569424172},{"storeID":98007,"salesPersonID":6,"cdID":621453,"pricePaid":13,"date":1649569424199},{"storeID":98046,"salesPersonID":21,"cdID":321456,"pricePaid":9,"date":1649569424225},{"storeID":98046,"salesPersonID":22,"cdID":123456,"pricePaid":14,"date":1649569424251},{"storeID":98077,"salesPersonID":11,"cdID":623451,"pricePaid":14,"date":1649569424281},{"storeID":98007,"salesPersonID":6,"cdID":354126,"pricePaid":7,"date":1649569424311},{"storeID":98077,"salesPersonID":11,"cdID":321654,"pricePaid":14,"date":1649569424337},{"storeID":98011,"salesPersonID":20,"cdID":123654,"pricePaid":11,"date":1649569424363},{"storeID":98077,"salesPersonID":9,"cdID":354126,"pricePaid":14,"date":1649569424389},{"storeID":98011,"salesPersonID":20,"cdID":123654,"pricePaid":15,"date":1649569424417},{"storeID":98053,"salesPersonID":1,"cdID":543216,"pricePaid":14,"date":1649569424446},{"storeID":98053,"salesPersonID":3,"cdID":623451,"pricePaid":11,"date":1649569424472},{"storeID":98011,"salesPersonID":20,"cdID":543216,"pricePaid":11,"date":1649569424500},{"storeID":98011,"salesPersonID":19,"cdID":321456,"pricePaid":7,"date":1649569424527},{"storeID":98007,"salesPersonID":7,"cdID":623451,"pricePaid":6,"date":1649569424555},{"storeID":98011,"salesPersonID":20,"cdID":321654,"pricePaid":6,"date":1649569424583},{"storeID":98046,"salesPersonID":21,"cdID":123456,"pricePaid":9,"date":1649569424612},{"storeID":98053,"salesPersonID":3,"cdID":123654,"pricePaid":15,"date":1649569424641},{"storeID":98011,"salesPersonID":17,"cdID":543216,"pricePaid":8,"date":1649569424668},{"storeID":98055,"salesPersonID":14,"cdID":623451,"pricePaid":12,"date":1649569424695},{"storeID":98077,"salesPersonID":12,"cdID":654123,"pricePaid":9,"date":1649569424724},{"storeID":98007,"salesPersonID":6,"cdID":543216,"pricePaid":14,"date":1649569424752},{"storeID":98011,"salesPersonID":18,"cdID":321654,"pricePaid":9,"date":1649569424778},{"storeID":98053,"salesPersonID":3,"cdID":621453,"pricePaid":11,"date":1649569424807},{"storeID":98055,"salesPersonID":13,"cdID":354126,"pricePaid":10,"date":1649569424835},{"storeID":98011,"salesPersonID":19,"cdID":623451,"pricePaid":11,"date":1649569424865},{"storeID":98055,"salesPersonID":16,"cdID":543216,"pricePaid":8,"date":1649569424892},{"storeID":98053,"salesPersonID":4,"cdID":123456,"pricePaid":7,"date":1649569424921},{"storeID":98011,"salesPersonID":17,"cdID":654123,"pricePaid":7,"date":1649569424948},{"storeID":98077,"salesPersonID":11,"cdID":321456,"pricePaid":7,"date":1649569424975},{"storeID":98055,"salesPersonID":13,"cdID":654321,"pricePaid":6,"date":1649569425002},{"storeID":98077,"salesPersonID":10,"cdID":654321,"pricePaid":12,"date":1649569425028},{"storeID":98077,"salesPersonID":11,"cdID":621453,"pricePaid":15,"date":1649569425056},{"storeID":98007,"salesPersonID":5,"cdID":621453,"pricePaid":7,"date":1649569425086},{"storeID":98055,"salesPersonID":16,"cdID":623451,"pricePaid":14,"date":1649569425114},{"storeID":98011,"salesPersonID":20,"cdID":321654,"pricePaid":8,"date":1649569425142},{"storeID":98055,"salesPersonID":15,"cdID":654123,"pricePaid":8,"date":1649569425168},{"storeID":98055,"salesPersonID":16,"cdID":123456,"pricePaid":10,"date":1649569425194},{"storeID":98077,"salesPersonID":11,"cdID":354126,"pricePaid":14,"date":1649569425223},{"storeID":98053,"salesPersonID":1,"cdID":321654,"pricePaid":9,"date":1649569425249},{"storeID":98053,"salesPersonID":4,"cdID":543216,"pricePaid":10,"date":1649569425278},{"storeID":98007,"salesPersonID":7,"cdID":654321,"pricePaid":13,"date":1649569425305},{"storeID":98011,"salesPersonID":17,"cdID":321456,"pricePaid":8,"date":1649569425333},{"storeID":98011,"salesPersonID":18,"cdID":621453,"pricePaid":7,"date":1649569425361},{"storeID":98077,"salesPersonID":12,"cdID":354126,"pricePaid":13,"date":1649569425388},{"storeID":98046,"salesPersonID":24,"cdID":123456,"pricePaid":5,"date":1649569425417}]